pyglvis/__init__.py
pyglvis/_version.py
pyglvis/widget.py
pyglvis/static/extension.js
pyglvis/static/index.js
pyglvis/static/index.js.map
pyglvis/static/package.json
pyglvis-0.1.2.data/data/etc/jupyter/nbconfig/notebook.d/jupyter-glvis.json
pyglvis-0.1.2.data/data/share/jupyter/nbextensions/jupyter-glvis/extension.js
pyglvis-0.1.2.data/data/share/jupyter/nbextensions/jupyter-glvis/index.js
pyglvis-0.1.2.data/data/share/jupyter/nbextensions/jupyter-glvis/index.js.map
pyglvis-0.1.2.data/data/share/jupyter/nbextensions/jupyter-glvis/package.json
pyglvis-0.1.2.dist-info/METADATA
pyglvis-0.1.2.dist-info/RECORD
pyglvis-0.1.2.dist-info/WHEEL
pyglvis-0.1.2.dist-info/top_level.txt
